simple_schema_validator/__init__.py
simple_schema_validator/__version__.py
simple_schema_validator/schema_types.py
simple_schema_validator/schema_validator.py
simple_schema_validator/tests.py
simple_schema_validator/utils.py
simple_schema_validator-0.0.9.dist-info/LICENSE
simple_schema_validator-0.0.9.dist-info/METADATA
simple_schema_validator-0.0.9.dist-info/WHEEL
simple_schema_validator-0.0.9.dist-info/top_level.txt
simple_schema_validator-0.0.9.dist-info/RECORD
