Metadata-Version: 2.1
Name: simple-schema-validator
Version: 0.0.9
Summary: A dead-simple utility that validates if object has a certain structure.
Home-page: https://github.com/HackSoftware/simple_schema_validator
Author: Radoslav Georgiev
Author-email: radorado@hacksoft.io
License: MIT
Platform: UNKNOWN
Classifier: License :: OSI Approved :: MIT License
Classifier: Programming Language :: Python
Classifier: Programming Language :: Python :: 3
Classifier: Programming Language :: Python :: 3.6
Classifier: Programming Language :: Python :: Implementation :: CPython
Requires-Python: >=3.6.0
